WallStreetSocial/__init__.py
WallStreetSocial/database.py
WallStreetSocial/helpers.py
WallStreetSocial/preprocess.py
wsb_ner/__init__.py
wsb_ner/ner/__init__.py
wsb_ner/vocab/__init__.py
WallStreetSocial-1.0.0.4.dist-info/LICENSE
WallStreetSocial-1.0.0.4.dist-info/METADATA
WallStreetSocial-1.0.0.4.dist-info/WHEEL
WallStreetSocial-1.0.0.4.dist-info/top_level.txt
WallStreetSocial-1.0.0.4.dist-info/RECORD
