Metadata-Version: 2.1
Name: WallStreetSocial
Version: 1.0.0.4
Summary: Is an open source piece of software that is designed to allow anyone to quickly get
Home-page: https://github.com/JGolafshan/WallStreetSocial
Author: ['Joshua David Golafshan', 'John Hutton']
Keywords: Database,WallStreetBets,Reddit
Classifier: Programming Language :: Python :: 3
Classifier: Operating System :: OS Independent
License-File: LICENSE
Requires-Dist: setuptools
Requires-Dist: yfinance
Requires-Dist: matplotlib
Requires-Dist: pandas
Requires-Dist: plotly
Requires-Dist: gensim
Requires-Dist: datetime
Requires-Dist: pmaw
Requires-Dist: spacy
Requires-Dist: vaderSentiment
Requires-Dist: numpy
Requires-Dist: nltk
Requires-Dist: requests
